CHANGELOG.txt
LICENSE
MANIFEST.in
README.rst
setup.cfg
setup.py
doc/Makefile
doc/conf.py
doc/example_hello.py
doc/index.rst
doc/intro.rst
doc/make.bat
doc/modules.rst
doc/modules/command.rst
doc/modules/log.rst
doc/modules/path.rst
doc/modules/shell.rst
scriptine/__init__.py
scriptine/_path.py
scriptine/command.py
scriptine/files.py
scriptine/log.py
scriptine/meta.py
scriptine/misc.py
scriptine/shell.py
scriptinep3.egg-info/PKG-INFO
scriptinep3.egg-info/SOURCES.txt
scriptinep3.egg-info/dependency_links.txt
scriptinep3.egg-info/not-zip-safe
scriptinep3.egg-info/requires.txt
scriptinep3.egg-info/top_level.txt
test/test_command.py
test/test_misc.py
test/test_path.py