Metadata-Version: 1.1
Name: scriptinep3
Version: 0.3.1
Summary: python shell scripts made easy - scriptine Ported to python 3
Home-page: https://github.com/bouke-nederstigt/scriptine
Author: Oliver Tonnhofer
Author-email: UNKNOWN
License: MIT License
Platform: UNKNOWN
Classifier: License :: OSI Approved :: MIT License
Classifier: Programming Language :: Python
